{
  "0": {
    "creationTime": "2020-01-05T15:47:40.5508513-06:00",
    "Walls": [
      {
        "Orientation": {
          "Name": "West",
          "foreUnit": -1.0,
          "rightUnit": 1.0,
          "Forward": {
            "x": -1.0,
            "y": 0.0,
            "z": 0.0
          },
          "Back": {
            "x": 1.0,
            "y": 0.0,
            "z": 0.0
          },
          "Left": {
            "x": 0.0,
            "y": -1.0,
            "z": 0.0
          },
          "Right": {
            "x": 0.0,
            "y": 1.0,
            "z": 0.0
          }
        },
        "Min": {
          "x": 21.0,
          "y": 24.0,
          "z": 1.0
        },
        "Max": {
          "x": 21.0,
          "y": 36.0,
          "z": 1.0
        },
        "DemoList": [
          [
            {
              "x": 21.0,
              "y": 29.0,
              "z": 1.0
            },
            {
              "x": 21.0,
              "y": 30.0,
              "z": 1.0
            }
          ]
        ],
        "Segments": [
          [
            {
              "x": 21.0,
              "y": 24.0,
              "z": 1.0
            },
            {
              "x": 21.0,
              "y": 25.0,
              "z": 1.0
            },
            {
              "x": 21.0,
              "y": 26.0,
              "z": 1.0
            },
            {
              "x": 21.0,
              "y": 27.0,
              "z": 1.0
            },
            {
              "x": 21.0,
              "y": 28.0,
              "z": 1.0
            },
            {
              "x": 21.0,
              "y": 29.0,
              "z": 1.0
            },
            {
              "x": 21.0,
              "y": 30.0,
              "z": 1.0
            },
            {
              "x": 21.0,
              "y": 31.0,
              "z": 1.0
            },
            {
              "x": 21.0,
              "y": 32.0,
              "z": 1.0
            },
            {
              "x": 21.0,
              "y": 33.0,
              "z": 1.0
            },
            {
              "x": 21.0,
              "y": 34.0,
              "z": 1.0
            },
            {
              "x": 21.0,
              "y": 35.0,
              "z": 1.0
            },
            {
              "x": 21.0,
              "y": 36.0,
              "z": 1.0
            }
          ]
        ]
      },
      {
        "Orientation": {
          "Name": "East",
          "foreUnit": 1.0,
          "rightUnit": -1.0,
          "Forward": {
            "x": 1.0,
            "y": 0.0,
            "z": 0.0
          },
          "Back": {
            "x": -1.0,
            "y": 0.0,
            "z": 0.0
          },
          "Left": {
            "x": 0.0,
            "y": 1.0,
            "z": 0.0
          },
          "Right": {
            "x": 0.0,
            "y": -1.0,
            "z": 0.0
          }
        },
        "Min": {
          "x": 29.0,
          "y": 24.0,
          "z": 1.0
        },
        "Max": {
          "x": 29.0,
          "y": 36.0,
          "z": 1.0
        },
        "DemoList": [
          [
            {
              "x": 29.0,
              "y": 30.0,
              "z": 1.0
            },
            {
              "x": 29.0,
              "y": 31.0,
              "z": 1.0
            },
            {
              "x": 29.0,
              "y": 32.0,
              "z": 1.0
            },
            {
              "x": 29.0,
              "y": 33.0,
              "z": 1.0
            },
            {
              "x": 29.0,
              "y": 34.0,
              "z": 1.0
            },
            {
              "x": 29.0,
              "y": 35.0,
              "z": 1.0
            }
          ]
        ],
        "Segments": [
          [
            {
              "x": 29.0,
              "y": 24.0,
              "z": 1.0
            },
            {
              "x": 29.0,
              "y": 25.0,
              "z": 1.0
            },
            {
              "x": 29.0,
              "y": 26.0,
              "z": 1.0
            },
            {
              "x": 29.0,
              "y": 27.0,
              "z": 1.0
            },
            {
              "x": 29.0,
              "y": 28.0,
              "z": 1.0
            },
            {
              "x": 29.0,
              "y": 29.0,
              "z": 1.0
            },
            {
              "x": 29.0,
              "y": 30.0,
              "z": 1.0
            },
            {
              "x": 29.0,
              "y": 31.0,
              "z": 1.0
            },
            {
              "x": 29.0,
              "y": 32.0,
              "z": 1.0
            },
            {
              "x": 29.0,
              "y": 33.0,
              "z": 1.0
            },
            {
              "x": 29.0,
              "y": 34.0,
              "z": 1.0
            },
            {
              "x": 29.0,
              "y": 35.0,
              "z": 1.0
            },
            {
              "x": 29.0,
              "y": 36.0,
              "z": 1.0
            }
          ]
        ]
      },
      {
        "Orientation": {
          "Name": "North",
          "foreUnit": 1.0,
          "rightUnit": 1.0,
          "Forward": {
            "x": 0.0,
            "y": 1.0,
            "z": 0.0
          },
          "Back": {
            "x": 0.0,
            "y": -1.0,
            "z": 0.0
          },
          "Left": {
            "x": -1.0,
            "y": 0.0,
            "z": 0.0
          },
          "Right": {
            "x": 1.0,
            "y": 0.0,
            "z": 0.0
          }
        },
        "Min": {
          "x": 21.0,
          "y": 36.0,
          "z": 1.0
        },
        "Max": {
          "x": 29.0,
          "y": 36.0,
          "z": 1.0
        },
        "DemoList": [],
        "Segments": [
          [
            {
              "x": 21.0,
              "y": 36.0,
              "z": 1.0
            },
            {
              "x": 22.0,
              "y": 36.0,
              "z": 1.0
            },
            {
              "x": 23.0,
              "y": 36.0,
              "z": 1.0
            },
            {
              "x": 24.0,
              "y": 36.0,
              "z": 1.0
            },
            {
              "x": 25.0,
              "y": 36.0,
              "z": 1.0
            },
            {
              "x": 26.0,
              "y": 36.0,
              "z": 1.0
            },
            {
              "x": 27.0,
              "y": 36.0,
              "z": 1.0
            },
            {
              "x": 28.0,
              "y": 36.0,
              "z": 1.0
            },
            {
              "x": 29.0,
              "y": 36.0,
              "z": 1.0
            }
          ]
        ]
      },
      {
        "Orientation": {
          "Name": "South",
          "foreUnit": -1.0,
          "rightUnit": -1.0,
          "Forward": {
            "x": 0.0,
            "y": -1.0,
            "z": 0.0
          },
          "Back": {
            "x": 0.0,
            "y": 1.0,
            "z": 0.0
          },
          "Left": {
            "x": 1.0,
            "y": 0.0,
            "z": 0.0
          },
          "Right": {
            "x": -1.0,
            "y": 0.0,
            "z": 0.0
          }
        },
        "Min": {
          "x": 21.0,
          "y": 24.0,
          "z": 1.0
        },
        "Max": {
          "x": 29.0,
          "y": 24.0,
          "z": 1.0
        },
        "DemoList": [
          [
            {
              "x": 26.0,
              "y": 24.0,
              "z": 1.0
            },
            {
              "x": 27.0,
              "y": 24.0,
              "z": 1.0
            },
            {
              "x": 28.0,
              "y": 24.0,
              "z": 1.0
            },
            {
              "x": 29.0,
              "y": 24.0,
              "z": 1.0
            }
          ]
        ],
        "Segments": [
          [
            {
              "x": 21.0,
              "y": 24.0,
              "z": 1.0
            },
            {
              "x": 22.0,
              "y": 24.0,
              "z": 1.0
            },
            {
              "x": 23.0,
              "y": 24.0,
              "z": 1.0
            },
            {
              "x": 24.0,
              "y": 24.0,
              "z": 1.0
            },
            {
              "x": 25.0,
              "y": 24.0,
              "z": 1.0
            },
            {
              "x": 26.0,
              "y": 24.0,
              "z": 1.0
            },
            {
              "x": 27.0,
              "y": 24.0,
              "z": 1.0
            },
            {
              "x": 28.0,
              "y": 24.0,
              "z": 1.0
            },
            {
              "x": 29.0,
              "y": 24.0,
              "z": 1.0
            }
          ]
        ]
      }
    ],
    "ConnectedAreas": [
      1,
      1,
      2,
      3,
      7
    ],
    "Orientation": {
      "Name": "North",
      "foreUnit": 1.0,
      "rightUnit": 1.0,
      "Forward": {
        "x": 0.0,
        "y": 1.0,
        "z": 0.0
      },
      "Back": {
        "x": 0.0,
        "y": -1.0,
        "z": 0.0
      },
      "Left": {
        "x": -1.0,
        "y": 0.0,
        "z": 0.0
      },
      "Right": {
        "x": 1.0,
        "y": 0.0,
        "z": 0.0
      }
    },
    "RoomIndex": 0,
    "Floor": {
      "BottomLeft": {
        "x": 22.0,
        "y": 25.0,
        "z": 1.0
      },
      "TopRight": {
        "x": 28.0,
        "y": 35.0,
        "z": 1.0
      },
      "BottomRight": {
        "x": 28.0,
        "y": 25.0,
        "z": 1.0
      },
      "TopLeft": {
        "x": 22.0,
        "y": 35.0,
        "z": 1.0
      },
      "width": 7.0,
      "height": 11.0,
      "Center": {
        "x": 25.5,
        "y": 30.5,
        "z": 1.0
      },
      "TrueSW": {
        "x": 22.0,
        "y": 25.0,
        "z": 1.0
      },
      "TrueNE": {
        "x": 28.0,
        "y": 35.0,
        "z": 1.0
      }
    }
  },
  "1": {
    "creationTime": "2020-01-05T15:47:40.5649397-06:00",
    "Walls": [
      {
        "Orientation": {
          "Name": "East",
          "foreUnit": 1.0,
          "rightUnit": -1.0,
          "Forward": {
            "x": 1.0,
            "y": 0.0,
            "z": 0.0
          },
          "Back": {
            "x": -1.0,
            "y": 0.0,
            "z": 0.0
          },
          "Left": {
            "x": 0.0,
            "y": 1.0,
            "z": 0.0
          },
          "Right": {
            "x": 0.0,
            "y": -1.0,
            "z": 0.0
          }
        },
        "Min": {
          "x": 21.0,
          "y": 27.0,
          "z": 1.0
        },
        "Max": {
          "x": 21.0,
          "y": 34.0,
          "z": 1.0
        },
        "DemoList": [
          [
            {
              "x": 21.0,
              "y": 33.0,
              "z": 1.0
            },
            {
              "x": 21.0,
              "y": 32.0,
              "z": 1.0
            },
            {
              "x": 21.0,
              "y": 31.0,
              "z": 1.0
            },
            {
              "x": 21.0,
              "y": 30.0,
              "z": 1.0
            },
            {
              "x": 21.0,
              "y": 29.0,
              "z": 1.0
            },
            {
              "x": 21.0,
              "y": 28.0,
              "z": 1.0
            }
          ]
        ],
        "Segments": [
          [
            {
              "x": 21.0,
              "y": 27.0,
              "z": 1.0
            },
            {
              "x": 21.0,
              "y": 28.0,
              "z": 1.0
            },
            {
              "x": 21.0,
              "y": 29.0,
              "z": 1.0
            },
            {
              "x": 21.0,
              "y": 30.0,
              "z": 1.0
            },
            {
              "x": 21.0,
              "y": 31.0,
              "z": 1.0
            },
            {
              "x": 21.0,
              "y": 32.0,
              "z": 1.0
            },
            {
              "x": 21.0,
              "y": 33.0,
              "z": 1.0
            },
            {
              "x": 21.0,
              "y": 34.0,
              "z": 1.0
            }
          ]
        ]
      },
      {
        "Orientation": {
          "Name": "South",
          "foreUnit": -1.0,
          "rightUnit": -1.0,
          "Forward": {
            "x": 0.0,
            "y": -1.0,
            "z": 0.0
          },
          "Back": {
            "x": 0.0,
            "y": 1.0,
            "z": 0.0
          },
          "Left": {
            "x": 1.0,
            "y": 0.0,
            "z": 0.0
          },
          "Right": {
            "x": -1.0,
            "y": 0.0,
            "z": 0.0
          }
        },
        "Min": {
          "x": 9.0,
          "y": 27.0,
          "z": 1.0
        },
        "Max": {
          "x": 21.0,
          "y": 27.0,
          "z": 1.0
        },
        "DemoList": [
          [
            {
              "x": 12.0,
              "y": 27.0,
              "z": 1.0
            },
            {
              "x": 13.0,
              "y": 27.0,
              "z": 1.0
            },
            {
              "x": 14.0,
              "y": 27.0,
              "z": 1.0
            },
            {
              "x": 15.0,
              "y": 27.0,
              "z": 1.0
            },
            {
              "x": 16.0,
              "y": 27.0,
              "z": 1.0
            },
            {
              "x": 17.0,
              "y": 27.0,
              "z": 1.0
            }
          ]
        ],
        "Segments": [
          [
            {
              "x": 9.0,
              "y": 27.0,
              "z": 1.0
            },
            {
              "x": 10.0,
              "y": 27.0,
              "z": 1.0
            },
            {
              "x": 11.0,
              "y": 27.0,
              "z": 1.0
            },
            {
              "x": 12.0,
              "y": 27.0,
              "z": 1.0
            },
            {
              "x": 13.0,
              "y": 27.0,
              "z": 1.0
            },
            {
              "x": 14.0,
              "y": 27.0,
              "z": 1.0
            },
            {
              "x": 15.0,
              "y": 27.0,
              "z": 1.0
            },
            {
              "x": 16.0,
              "y": 27.0,
              "z": 1.0
            },
            {
              "x": 17.0,
              "y": 27.0,
              "z": 1.0
            },
            {
              "x": 18.0,
              "y": 27.0,
              "z": 1.0
            },
            {
              "x": 19.0,
              "y": 27.0,
              "z": 1.0
            },
            {
              "x": 20.0,
              "y": 27.0,
              "z": 1.0
            },
            {
              "x": 21.0,
              "y": 27.0,
              "z": 1.0
            }
          ]
        ]
      },
      {
        "Orientation": {
          "Name": "North",
          "foreUnit": 1.0,
          "rightUnit": 1.0,
          "Forward": {
            "x": 0.0,
            "y": 1.0,
            "z": 0.0
          },
          "Back": {
            "x": 0.0,
            "y": -1.0,
            "z": 0.0
          },
          "Left": {
            "x": -1.0,
            "y": 0.0,
            "z": 0.0
          },
          "Right": {
            "x": 1.0,
            "y": 0.0,
            "z": 0.0
          }
        },
        "Min": {
          "x": 9.0,
          "y": 34.0,
          "z": 1.0
        },
        "Max": {
          "x": 21.0,
          "y": 34.0,
          "z": 1.0
        },
        "DemoList": [],
        "Segments": [
          [
            {
              "x": 9.0,
              "y": 34.0,
              "z": 1.0
            },
            {
              "x": 10.0,
              "y": 34.0,
              "z": 1.0
            },
            {
              "x": 11.0,
              "y": 34.0,
              "z": 1.0
            },
            {
              "x": 12.0,
              "y": 34.0,
              "z": 1.0
            },
            {
              "x": 13.0,
              "y": 34.0,
              "z": 1.0
            },
            {
              "x": 14.0,
              "y": 34.0,
              "z": 1.0
            },
            {
              "x": 15.0,
              "y": 34.0,
              "z": 1.0
            },
            {
              "x": 16.0,
              "y": 34.0,
              "z": 1.0
            },
            {
              "x": 17.0,
              "y": 34.0,
              "z": 1.0
            },
            {
              "x": 18.0,
              "y": 34.0,
              "z": 1.0
            },
            {
              "x": 19.0,
              "y": 34.0,
              "z": 1.0
            },
            {
              "x": 20.0,
              "y": 34.0,
              "z": 1.0
            },
            {
              "x": 21.0,
              "y": 34.0,
              "z": 1.0
            }
          ]
        ]
      },
      {
        "Orientation": {
          "Name": "West",
          "foreUnit": -1.0,
          "rightUnit": 1.0,
          "Forward": {
            "x": -1.0,
            "y": 0.0,
            "z": 0.0
          },
          "Back": {
            "x": 1.0,
            "y": 0.0,
            "z": 0.0
          },
          "Left": {
            "x": 0.0,
            "y": -1.0,
            "z": 0.0
          },
          "Right": {
            "x": 0.0,
            "y": 1.0,
            "z": 0.0
          }
        },
        "Min": {
          "x": 9.0,
          "y": 27.0,
          "z": 1.0
        },
        "Max": {
          "x": 9.0,
          "y": 34.0,
          "z": 1.0
        },
        "DemoList": [],
        "Segments": [
          [
            {
              "x": 9.0,
              "y": 27.0,
              "z": 1.0
            },
            {
              "x": 9.0,
              "y": 28.0,
              "z": 1.0
            },
            {
              "x": 9.0,
              "y": 29.0,
              "z": 1.0
            },
            {
              "x": 9.0,
              "y": 30.0,
              "z": 1.0
            },
            {
              "x": 9.0,
              "y": 31.0,
              "z": 1.0
            },
            {
              "x": 9.0,
              "y": 32.0,
              "z": 1.0
            },
            {
              "x": 9.0,
              "y": 33.0,
              "z": 1.0
            },
            {
              "x": 9.0,
              "y": 34.0,
              "z": 1.0
            }
          ]
        ]
      }
    ],
    "ConnectedAreas": [
      0,
      4,
      7,
      7
    ],
    "Orientation": {
      "Name": "West",
      "foreUnit": -1.0,
      "rightUnit": 1.0,
      "Forward": {
        "x": -1.0,
        "y": 0.0,
        "z": 0.0
      },
      "Back": {
        "x": 1.0,
        "y": 0.0,
        "z": 0.0
      },
      "Left": {
        "x": 0.0,
        "y": -1.0,
        "z": 0.0
      },
      "Right": {
        "x": 0.0,
        "y": 1.0,
        "z": 0.0
      }
    },
    "RoomIndex": 1,
    "Floor": {
      "BottomLeft": {
        "x": 20.0,
        "y": 28.0,
        "z": 1.0
      },
      "TopRight": {
        "x": 10.0,
        "y": 33.0,
        "z": 1.0
      },
      "BottomRight": {
        "x": 20.0,
        "y": 33.0,
        "z": 1.0
      },
      "TopLeft": {
        "x": 10.0,
        "y": 28.0,
        "z": 1.0
      },
      "width": 6.0,
      "height": 11.0,
      "Center": {
        "x": 23.0,
        "y": 38.5,
        "z": 1.0
      },
      "TrueSW": {
        "x": 10.0,
        "y": 28.0,
        "z": 1.0
      },
      "TrueNE": {
        "x": 20.0,
        "y": 33.0,
        "z": 1.0
      }
    }
  },
  "2": {
    "creationTime": "2020-01-05T15:47:40.5668872-06:00",
    "Walls": [
      {
        "Orientation": {
          "Name": "North",
          "foreUnit": 1.0,
          "rightUnit": 1.0,
          "Forward": {
            "x": 0.0,
            "y": 1.0,
            "z": 0.0
          },
          "Back": {
            "x": 0.0,
            "y": -1.0,
            "z": 0.0
          },
          "Left": {
            "x": -1.0,
            "y": 0.0,
            "z": 0.0
          },
          "Right": {
            "x": 1.0,
            "y": 0.0,
            "z": 0.0
          }
        },
        "Min": {
          "x": 29.0,
          "y": 35.0,
          "z": 1.0
        },
        "Max": {
          "x": 43.0,
          "y": 35.0,
          "z": 1.0
        },
        "DemoList": [
          [
            {
              "x": 32.0,
              "y": 35.0,
              "z": 1.0
            },
            {
              "x": 33.0,
              "y": 35.0,
              "z": 1.0
            }
          ]
        ],
        "Segments": [
          [
            {
              "x": 29.0,
              "y": 35.0,
              "z": 1.0
            },
            {
              "x": 30.0,
              "y": 35.0,
              "z": 1.0
            },
            {
              "x": 31.0,
              "y": 35.0,
              "z": 1.0
            },
            {
              "x": 32.0,
              "y": 35.0,
              "z": 1.0
            },
            {
              "x": 33.0,
              "y": 35.0,
              "z": 1.0
            },
            {
              "x": 34.0,
              "y": 35.0,
              "z": 1.0
            },
            {
              "x": 35.0,
              "y": 35.0,
              "z": 1.0
            },
            {
              "x": 36.0,
              "y": 35.0,
              "z": 1.0
            },
            {
              "x": 37.0,
              "y": 35.0,
              "z": 1.0
            },
            {
              "x": 38.0,
              "y": 35.0,
              "z": 1.0
            },
            {
              "x": 39.0,
              "y": 35.0,
              "z": 1.0
            },
            {
              "x": 40.0,
              "y": 35.0,
              "z": 1.0
            },
            {
              "x": 41.0,
              "y": 35.0,
              "z": 1.0
            },
            {
              "x": 42.0,
              "y": 35.0,
              "z": 1.0
            },
            {
              "x": 43.0,
              "y": 35.0,
              "z": 1.0
            }
          ]
        ]
      },
      {
        "Orientation": {
          "Name": "South",
          "foreUnit": -1.0,
          "rightUnit": -1.0,
          "Forward": {
            "x": 0.0,
            "y": -1.0,
            "z": 0.0
          },
          "Back": {
            "x": 0.0,
            "y": 1.0,
            "z": 0.0
          },
          "Left": {
            "x": 1.0,
            "y": 0.0,
            "z": 0.0
          },
          "Right": {
            "x": -1.0,
            "y": 0.0,
            "z": 0.0
          }
        },
        "Min": {
          "x": 29.0,
          "y": 27.0,
          "z": 1.0
        },
        "Max": {
          "x": 43.0,
          "y": 27.0,
          "z": 1.0
        },
        "DemoList": [],
        "Segments": [
          [
            {
              "x": 29.0,
              "y": 27.0,
              "z": 1.0
            },
            {
              "x": 30.0,
              "y": 27.0,
              "z": 1.0
            },
            {
              "x": 31.0,
              "y": 27.0,
              "z": 1.0
            },
            {
              "x": 32.0,
              "y": 27.0,
              "z": 1.0
            },
            {
              "x": 33.0,
              "y": 27.0,
              "z": 1.0
            },
            {
              "x": 34.0,
              "y": 27.0,
              "z": 1.0
            },
            {
              "x": 35.0,
              "y": 27.0,
              "z": 1.0
            },
            {
              "x": 36.0,
              "y": 27.0,
              "z": 1.0
            },
            {
              "x": 37.0,
              "y": 27.0,
              "z": 1.0
            },
            {
              "x": 38.0,
              "y": 27.0,
              "z": 1.0
            },
            {
              "x": 39.0,
              "y": 27.0,
              "z": 1.0
            },
            {
              "x": 40.0,
              "y": 27.0,
              "z": 1.0
            },
            {
              "x": 41.0,
              "y": 27.0,
              "z": 1.0
            },
            {
              "x": 42.0,
              "y": 27.0,
              "z": 1.0
            },
            {
              "x": 43.0,
              "y": 27.0,
              "z": 1.0
            }
          ]
        ]
      },
      {
        "Orientation": {
          "Name": "West",
          "foreUnit": -1.0,
          "rightUnit": 1.0,
          "Forward": {
            "x": -1.0,
            "y": 0.0,
            "z": 0.0
          },
          "Back": {
            "x": 1.0,
            "y": 0.0,
            "z": 0.0
          },
          "Left": {
            "x": 0.0,
            "y": -1.0,
            "z": 0.0
          },
          "Right": {
            "x": 0.0,
            "y": 1.0,
            "z": 0.0
          }
        },
        "Min": {
          "x": 29.0,
          "y": 27.0,
          "z": 1.0
        },
        "Max": {
          "x": 29.0,
          "y": 35.0,
          "z": 1.0
        },
        "DemoList": [
          [
            {
              "x": 29.0,
              "y": 28.0,
              "z": 1.0
            },
            {
              "x": 29.0,
              "y": 29.0,
              "z": 1.0
            },
            {
              "x": 29.0,
              "y": 30.0,
              "z": 1.0
            },
            {
              "x": 29.0,
              "y": 31.0,
              "z": 1.0
            },
            {
              "x": 29.0,
              "y": 32.0,
              "z": 1.0
            },
            {
              "x": 29.0,
              "y": 33.0,
              "z": 1.0
            },
            {
              "x": 29.0,
              "y": 34.0,
              "z": 1.0
            }
          ]
        ],
        "Segments": [
          [
            {
              "x": 29.0,
              "y": 27.0,
              "z": 1.0
            },
            {
              "x": 29.0,
              "y": 28.0,
              "z": 1.0
            },
            {
              "x": 29.0,
              "y": 29.0,
              "z": 1.0
            },
            {
              "x": 29.0,
              "y": 30.0,
              "z": 1.0
            },
            {
              "x": 29.0,
              "y": 31.0,
              "z": 1.0
            },
            {
              "x": 29.0,
              "y": 32.0,
              "z": 1.0
            },
            {
              "x": 29.0,
              "y": 33.0,
              "z": 1.0
            },
            {
              "x": 29.0,
              "y": 34.0,
              "z": 1.0
            },
            {
              "x": 29.0,
              "y": 35.0,
              "z": 1.0
            }
          ]
        ]
      },
      {
        "Orientation": {
          "Name": "East",
          "foreUnit": 1.0,
          "rightUnit": -1.0,
          "Forward": {
            "x": 1.0,
            "y": 0.0,
            "z": 0.0
          },
          "Back": {
            "x": -1.0,
            "y": 0.0,
            "z": 0.0
          },
          "Left": {
            "x": 0.0,
            "y": 1.0,
            "z": 0.0
          },
          "Right": {
            "x": 0.0,
            "y": -1.0,
            "z": 0.0
          }
        },
        "Min": {
          "x": 43.0,
          "y": 27.0,
          "z": 1.0
        },
        "Max": {
          "x": 43.0,
          "y": 35.0,
          "z": 1.0
        },
        "DemoList": [],
        "Segments": [
          [
            {
              "x": 43.0,
              "y": 27.0,
              "z": 1.0
            },
            {
              "x": 43.0,
              "y": 28.0,
              "z": 1.0
            },
            {
              "x": 43.0,
              "y": 29.0,
              "z": 1.0
            },
            {
              "x": 43.0,
              "y": 30.0,
              "z": 1.0
            },
            {
              "x": 43.0,
              "y": 31.0,
              "z": 1.0
            },
            {
              "x": 43.0,
              "y": 32.0,
              "z": 1.0
            },
            {
              "x": 43.0,
              "y": 33.0,
              "z": 1.0
            },
            {
              "x": 43.0,
              "y": 34.0,
              "z": 1.0
            },
            {
              "x": 43.0,
              "y": 35.0,
              "z": 1.0
            }
          ]
        ]
      }
    ],
    "ConnectedAreas": [
      0,
      8
    ],
    "Orientation": {
      "Name": "East",
      "foreUnit": 1.0,
      "rightUnit": -1.0,
      "Forward": {
        "x": 1.0,
        "y": 0.0,
        "z": 0.0
      },
      "Back": {
        "x": -1.0,
        "y": 0.0,
        "z": 0.0
      },
      "Left": {
        "x": 0.0,
        "y": 1.0,
        "z": 0.0
      },
      "Right": {
        "x": 0.0,
        "y": -1.0,
        "z": 0.0
      }
    },
    "RoomIndex": 2,
    "Floor": {
      "BottomLeft": {
        "x": 30.0,
        "y": 34.0,
        "z": 1.0
      },
      "TopRight": {
        "x": 42.0,
        "y": 28.0,
        "z": 1.0
      },
      "BottomRight": {
        "x": 30.0,
        "y": 28.0,
        "z": 1.0
      },
      "TopLeft": {
        "x": 42.0,
        "y": 34.0,
        "z": 1.0
      },
      "width": 7.0,
      "height": 13.0,
      "Center": {
        "x": 33.5,
        "y": 34.5,
        "z": 1.0
      },
      "TrueSW": {
        "x": 30.0,
        "y": 28.0,
        "z": 1.0
      },
      "TrueNE": {
        "x": 42.0,
        "y": 34.0,
        "z": 1.0
      }
    }
  },
  "3": {
    "creationTime": "2020-01-05T15:47:40.5668872-06:00",
    "Walls": [
      {
        "Orientation": {
          "Name": "West",
          "foreUnit": -1.0,
          "rightUnit": 1.0,
          "Forward": {
            "x": -1.0,
            "y": 0.0,
            "z": 0.0
          },
          "Back": {
            "x": 1.0,
            "y": 0.0,
            "z": 0.0
          },
          "Left": {
            "x": 0.0,
            "y": -1.0,
            "z": 0.0
          },
          "Right": {
            "x": 0.0,
            "y": 1.0,
            "z": 0.0
          }
        },
        "Min": {
          "x": 24.0,
          "y": 16.0,
          "z": 1.0
        },
        "Max": {
          "x": 24.0,
          "y": 24.0,
          "z": 1.0
        },
        "DemoList": [],
        "Segments": [
          [
            {
              "x": 24.0,
              "y": 16.0,
              "z": 1.0
            },
            {
              "x": 24.0,
              "y": 17.0,
              "z": 1.0
            },
            {
              "x": 24.0,
              "y": 18.0,
              "z": 1.0
            },
            {
              "x": 24.0,
              "y": 19.0,
              "z": 1.0
            },
            {
              "x": 24.0,
              "y": 20.0,
              "z": 1.0
            },
            {
              "x": 24.0,
              "y": 21.0,
              "z": 1.0
            },
            {
              "x": 24.0,
              "y": 22.0,
              "z": 1.0
            },
            {
              "x": 24.0,
              "y": 23.0,
              "z": 1.0
            },
            {
              "x": 24.0,
              "y": 24.0,
              "z": 1.0
            }
          ]
        ]
      },
      {
        "Orientation": {
          "Name": "South",
          "foreUnit": -1.0,
          "rightUnit": -1.0,
          "Forward": {
            "x": 0.0,
            "y": -1.0,
            "z": 0.0
          },
          "Back": {
            "x": 0.0,
            "y": 1.0,
            "z": 0.0
          },
          "Left": {
            "x": 1.0,
            "y": 0.0,
            "z": 0.0
          },
          "Right": {
            "x": -1.0,
            "y": 0.0,
            "z": 0.0
          }
        },
        "Min": {
          "x": 24.0,
          "y": 16.0,
          "z": 1.0
        },
        "Max": {
          "x": 34.0,
          "y": 16.0,
          "z": 1.0
        },
        "DemoList": [
          [
            {
              "x": 26.0,
              "y": 16.0,
              "z": 1.0
            },
            {
              "x": 27.0,
              "y": 16.0,
              "z": 1.0
            },
            {
              "x": 28.0,
              "y": 16.0,
              "z": 1.0
            },
            {
              "x": 29.0,
              "y": 16.0,
              "z": 1.0
            },
            {
              "x": 30.0,
              "y": 16.0,
              "z": 1.0
            }
          ]
        ],
        "Segments": [
          [
            {
              "x": 24.0,
              "y": 16.0,
              "z": 1.0
            },
            {
              "x": 25.0,
              "y": 16.0,
              "z": 1.0
            },
            {
              "x": 26.0,
              "y": 16.0,
              "z": 1.0
            },
            {
              "x": 27.0,
              "y": 16.0,
              "z": 1.0
            },
            {
              "x": 28.0,
              "y": 16.0,
              "z": 1.0
            },
            {
              "x": 29.0,
              "y": 16.0,
              "z": 1.0
            },
            {
              "x": 30.0,
              "y": 16.0,
              "z": 1.0
            },
            {
              "x": 31.0,
              "y": 16.0,
              "z": 1.0
            },
            {
              "x": 32.0,
              "y": 16.0,
              "z": 1.0
            },
            {
              "x": 33.0,
              "y": 16.0,
              "z": 1.0
            },
            {
              "x": 34.0,
              "y": 16.0,
              "z": 1.0
            }
          ]
        ]
      },
      {
        "Orientation": {
          "Name": "East",
          "foreUnit": 1.0,
          "rightUnit": -1.0,
          "Forward": {
            "x": 1.0,
            "y": 0.0,
            "z": 0.0
          },
          "Back": {
            "x": -1.0,
            "y": 0.0,
            "z": 0.0
          },
          "Left": {
            "x": 0.0,
            "y": 1.0,
            "z": 0.0
          },
          "Right": {
            "x": 0.0,
            "y": -1.0,
            "z": 0.0
          }
        },
        "Min": {
          "x": 34.0,
          "y": 16.0,
          "z": 1.0
        },
        "Max": {
          "x": 34.0,
          "y": 24.0,
          "z": 1.0
        },
        "DemoList": [],
        "Segments": [
          [
            {
              "x": 34.0,
              "y": 16.0,
              "z": 1.0
            },
            {
              "x": 34.0,
              "y": 17.0,
              "z": 1.0
            },
            {
              "x": 34.0,
              "y": 18.0,
              "z": 1.0
            },
            {
              "x": 34.0,
              "y": 19.0,
              "z": 1.0
            },
            {
              "x": 34.0,
              "y": 20.0,
              "z": 1.0
            },
            {
              "x": 34.0,
              "y": 21.0,
              "z": 1.0
            },
            {
              "x": 34.0,
              "y": 22.0,
              "z": 1.0
            },
            {
              "x": 34.0,
              "y": 23.0,
              "z": 1.0
            },
            {
              "x": 34.0,
              "y": 24.0,
              "z": 1.0
            }
          ]
        ]
      },
      {
        "Orientation": {
          "Name": "North",
          "foreUnit": 1.0,
          "rightUnit": 1.0,
          "Forward": {
            "x": 0.0,
            "y": 1.0,
            "z": 0.0
          },
          "Back": {
            "x": 0.0,
            "y": -1.0,
            "z": 0.0
          },
          "Left": {
            "x": -1.0,
            "y": 0.0,
            "z": 0.0
          },
          "Right": {
            "x": 1.0,
            "y": 0.0,
            "z": 0.0
          }
        },
        "Min": {
          "x": 24.0,
          "y": 24.0,
          "z": 1.0
        },
        "Max": {
          "x": 34.0,
          "y": 24.0,
          "z": 1.0
        },
        "DemoList": [
          [
            {
              "x": 25.0,
              "y": 24.0,
              "z": 1.0
            },
            {
              "x": 26.0,
              "y": 24.0,
              "z": 1.0
            },
            {
              "x": 27.0,
              "y": 24.0,
              "z": 1.0
            },
            {
              "x": 28.0,
              "y": 24.0,
              "z": 1.0
            }
          ]
        ],
        "Segments": [
          [
            {
              "x": 24.0,
              "y": 24.0,
              "z": 1.0
            },
            {
              "x": 25.0,
              "y": 24.0,
              "z": 1.0
            },
            {
              "x": 26.0,
              "y": 24.0,
              "z": 1.0
            },
            {
              "x": 27.0,
              "y": 24.0,
              "z": 1.0
            },
            {
              "x": 28.0,
              "y": 24.0,
              "z": 1.0
            },
            {
              "x": 29.0,
              "y": 24.0,
              "z": 1.0
            },
            {
              "x": 30.0,
              "y": 24.0,
              "z": 1.0
            },
            {
              "x": 31.0,
              "y": 24.0,
              "z": 1.0
            },
            {
              "x": 32.0,
              "y": 24.0,
              "z": 1.0
            },
            {
              "x": 33.0,
              "y": 24.0,
              "z": 1.0
            },
            {
              "x": 34.0,
              "y": 24.0,
              "z": 1.0
            }
          ]
        ]
      }
    ],
    "ConnectedAreas": [
      0,
      7
    ],
    "Orientation": {
      "Name": "South",
      "foreUnit": -1.0,
      "rightUnit": -1.0,
      "Forward": {
        "x": 0.0,
        "y": -1.0,
        "z": 0.0
      },
      "Back": {
        "x": 0.0,
        "y": 1.0,
        "z": 0.0
      },
      "Left": {
        "x": 1.0,
        "y": 0.0,
        "z": 0.0
      },
      "Right": {
        "x": -1.0,
        "y": 0.0,
        "z": 0.0
      }
    },
    "RoomIndex": 3,
    "Floor": {
      "BottomLeft": {
        "x": 33.0,
        "y": 23.0,
        "z": 1.0
      },
      "TopRight": {
        "x": 25.0,
        "y": 17.0,
        "z": 1.0
      },
      "BottomRight": {
        "x": 25.0,
        "y": 23.0,
        "z": 1.0
      },
      "TopLeft": {
        "x": 33.0,
        "y": 17.0,
        "z": 1.0
      },
      "width": 9.0,
      "height": 7.0,
      "Center": {
        "x": 37.5,
        "y": 26.5,
        "z": 1.0
      },
      "TrueSW": {
        "x": 25.0,
        "y": 17.0,
        "z": 1.0
      },
      "TrueNE": {
        "x": 33.0,
        "y": 23.0,
        "z": 1.0
      }
    }
  },
  "4": {
    "creationTime": "2020-01-05T15:47:40.5678869-06:00",
    "Walls": [
      {
        "Orientation": {
          "Name": "South",
          "foreUnit": -1.0,
          "rightUnit": -1.0,
          "Forward": {
            "x": 0.0,
            "y": -1.0,
            "z": 0.0
          },
          "Back": {
            "x": 0.0,
            "y": 1.0,
            "z": 0.0
          },
          "Left": {
            "x": 1.0,
            "y": 0.0,
            "z": 0.0
          },
          "Right": {
            "x": -1.0,
            "y": 0.0,
            "z": 0.0
          }
        },
        "Min": {
          "x": 10.0,
          "y": 17.0,
          "z": 1.0
        },
        "Max": {
          "x": 17.0,
          "y": 17.0,
          "z": 1.0
        },
        "DemoList": [
          [
            {
              "x": 15.0,
              "y": 17.0,
              "z": 1.0
            },
            {
              "x": 16.0,
              "y": 17.0,
              "z": 1.0
            },
            {
              "x": 17.0,
              "y": 17.0,
              "z": 1.0
            }
          ]
        ],
        "Segments": [
          [
            {
              "x": 10.0,
              "y": 17.0,
              "z": 1.0
            },
            {
              "x": 11.0,
              "y": 17.0,
              "z": 1.0
            },
            {
              "x": 12.0,
              "y": 17.0,
              "z": 1.0
            },
            {
              "x": 13.0,
              "y": 17.0,
              "z": 1.0
            },
            {
              "x": 14.0,
              "y": 17.0,
              "z": 1.0
            },
            {
              "x": 15.0,
              "y": 17.0,
              "z": 1.0
            },
            {
              "x": 16.0,
              "y": 17.0,
              "z": 1.0
            },
            {
              "x": 17.0,
              "y": 17.0,
              "z": 1.0
            }
          ]
        ]
      },
      {
        "Orientation": {
          "Name": "West",
          "foreUnit": -1.0,
          "rightUnit": 1.0,
          "Forward": {
            "x": -1.0,
            "y": 0.0,
            "z": 0.0
          },
          "Back": {
            "x": 1.0,
            "y": 0.0,
            "z": 0.0
          },
          "Left": {
            "x": 0.0,
            "y": -1.0,
            "z": 0.0
          },
          "Right": {
            "x": 0.0,
            "y": 1.0,
            "z": 0.0
          }
        },
        "Min": {
          "x": 10.0,
          "y": 17.0,
          "z": 1.0
        },
        "Max": {
          "x": 10.0,
          "y": 27.0,
          "z": 1.0
        },
        "DemoList": [],
        "Segments": [
          [
            {
              "x": 10.0,
              "y": 17.0,
              "z": 1.0
            },
            {
              "x": 10.0,
              "y": 18.0,
              "z": 1.0
            },
            {
              "x": 10.0,
              "y": 19.0,
              "z": 1.0
            },
            {
              "x": 10.0,
              "y": 20.0,
              "z": 1.0
            },
            {
              "x": 10.0,
              "y": 21.0,
              "z": 1.0
            },
            {
              "x": 10.0,
              "y": 22.0,
              "z": 1.0
            },
            {
              "x": 10.0,
              "y": 23.0,
              "z": 1.0
            },
            {
              "x": 10.0,
              "y": 24.0,
              "z": 1.0
            },
            {
              "x": 10.0,
              "y": 25.0,
              "z": 1.0
            },
            {
              "x": 10.0,
              "y": 26.0,
              "z": 1.0
            },
            {
              "x": 10.0,
              "y": 27.0,
              "z": 1.0
            }
          ]
        ]
      },
      {
        "Orientation": {
          "Name": "East",
          "foreUnit": 1.0,
          "rightUnit": -1.0,
          "Forward": {
            "x": 1.0,
            "y": 0.0,
            "z": 0.0
          },
          "Back": {
            "x": -1.0,
            "y": 0.0,
            "z": 0.0
          },
          "Left": {
            "x": 0.0,
            "y": 1.0,
            "z": 0.0
          },
          "Right": {
            "x": 0.0,
            "y": -1.0,
            "z": 0.0
          }
        },
        "Min": {
          "x": 17.0,
          "y": 17.0,
          "z": 1.0
        },
        "Max": {
          "x": 17.0,
          "y": 27.0,
          "z": 1.0
        },
        "DemoList": [],
        "Segments": [
          [
            {
              "x": 17.0,
              "y": 17.0,
              "z": 1.0
            },
            {
              "x": 17.0,
              "y": 18.0,
              "z": 1.0
            },
            {
              "x": 17.0,
              "y": 19.0,
              "z": 1.0
            },
            {
              "x": 17.0,
              "y": 20.0,
              "z": 1.0
            },
            {
              "x": 17.0,
              "y": 21.0,
              "z": 1.0
            },
            {
              "x": 17.0,
              "y": 22.0,
              "z": 1.0
            },
            {
              "x": 17.0,
              "y": 23.0,
              "z": 1.0
            },
            {
              "x": 17.0,
              "y": 24.0,
              "z": 1.0
            },
            {
              "x": 17.0,
              "y": 25.0,
              "z": 1.0
            },
            {
              "x": 17.0,
              "y": 26.0,
              "z": 1.0
            },
            {
              "x": 17.0,
              "y": 27.0,
              "z": 1.0
            }
          ]
        ]
      },
      {
        "Orientation": {
          "Name": "North",
          "foreUnit": 1.0,
          "rightUnit": 1.0,
          "Forward": {
            "x": 0.0,
            "y": 1.0,
            "z": 0.0
          },
          "Back": {
            "x": 0.0,
            "y": -1.0,
            "z": 0.0
          },
          "Left": {
            "x": -1.0,
            "y": 0.0,
            "z": 0.0
          },
          "Right": {
            "x": 1.0,
            "y": 0.0,
            "z": 0.0
          }
        },
        "Min": {
          "x": 10.0,
          "y": 27.0,
          "z": 1.0
        },
        "Max": {
          "x": 17.0,
          "y": 27.0,
          "z": 1.0
        },
        "DemoList": [
          [
            {
              "x": 11.0,
              "y": 27.0,
              "z": 1.0
            },
            {
              "x": 12.0,
              "y": 27.0,
              "z": 1.0
            },
            {
              "x": 13.0,
              "y": 27.0,
              "z": 1.0
            },
            {
              "x": 14.0,
              "y": 27.0,
              "z": 1.0
            },
            {
              "x": 15.0,
              "y": 27.0,
              "z": 1.0
            },
            {
              "x": 16.0,
              "y": 27.0,
              "z": 1.0
            }
          ]
        ],
        "Segments": [
          [
            {
              "x": 10.0,
              "y": 27.0,
              "z": 1.0
            },
            {
              "x": 11.0,
              "y": 27.0,
              "z": 1.0
            },
            {
              "x": 12.0,
              "y": 27.0,
              "z": 1.0
            },
            {
              "x": 13.0,
              "y": 27.0,
              "z": 1.0
            },
            {
              "x": 14.0,
              "y": 27.0,
              "z": 1.0
            },
            {
              "x": 15.0,
              "y": 27.0,
              "z": 1.0
            },
            {
              "x": 16.0,
              "y": 27.0,
              "z": 1.0
            },
            {
              "x": 17.0,
              "y": 27.0,
              "z": 1.0
            }
          ]
        ]
      }
    ],
    "ConnectedAreas": [
      1,
      5
    ],
    "Orientation": {
      "Name": "South",
      "foreUnit": -1.0,
      "rightUnit": -1.0,
      "Forward": {
        "x": 0.0,
        "y": -1.0,
        "z": 0.0
      },
      "Back": {
        "x": 0.0,
        "y": 1.0,
        "z": 0.0
      },
      "Left": {
        "x": 1.0,
        "y": 0.0,
        "z": 0.0
      },
      "Right": {
        "x": -1.0,
        "y": 0.0,
        "z": 0.0
      }
    },
    "RoomIndex": 4,
    "Floor": {
      "BottomLeft": {
        "x": 16.0,
        "y": 26.0,
        "z": 1.0
      },
      "TopRight": {
        "x": 11.0,
        "y": 18.0,
        "z": 1.0
      },
      "BottomRight": {
        "x": 11.0,
        "y": 26.0,
        "z": 1.0
      },
      "TopLeft": {
        "x": 16.0,
        "y": 18.0,
        "z": 1.0
      },
      "width": 6.0,
      "height": 9.0,
      "Center": {
        "x": 19.0,
        "y": 30.5,
        "z": 1.0
      },
      "TrueSW": {
        "x": 11.0,
        "y": 18.0,
        "z": 1.0
      },
      "TrueNE": {
        "x": 16.0,
        "y": 26.0,
        "z": 1.0
      }
    }
  },
  "5": {
    "creationTime": "2020-01-05T15:47:40.5678869-06:00",
    "Walls": [
      {
        "Orientation": {
          "Name": "South",
          "foreUnit": -1.0,
          "rightUnit": -1.0,
          "Forward": {
            "x": 0.0,
            "y": -1.0,
            "z": 0.0
          },
          "Back": {
            "x": 0.0,
            "y": 1.0,
            "z": 0.0
          },
          "Left": {
            "x": 1.0,
            "y": 0.0,
            "z": 0.0
          },
          "Right": {
            "x": -1.0,
            "y": 0.0,
            "z": 0.0
          }
        },
        "Min": {
          "x": 11.0,
          "y": 9.0,
          "z": 1.0
        },
        "Max": {
          "x": 20.0,
          "y": 9.0,
          "z": 1.0
        },
        "DemoList": [],
        "Segments": [
          [
            {
              "x": 11.0,
              "y": 9.0,
              "z": 1.0
            },
            {
              "x": 12.0,
              "y": 9.0,
              "z": 1.0
            },
            {
              "x": 13.0,
              "y": 9.0,
              "z": 1.0
            },
            {
              "x": 14.0,
              "y": 9.0,
              "z": 1.0
            },
            {
              "x": 15.0,
              "y": 9.0,
              "z": 1.0
            },
            {
              "x": 16.0,
              "y": 9.0,
              "z": 1.0
            },
            {
              "x": 17.0,
              "y": 9.0,
              "z": 1.0
            },
            {
              "x": 18.0,
              "y": 9.0,
              "z": 1.0
            },
            {
              "x": 19.0,
              "y": 9.0,
              "z": 1.0
            },
            {
              "x": 20.0,
              "y": 9.0,
              "z": 1.0
            }
          ]
        ]
      },
      {
        "Orientation": {
          "Name": "North",
          "foreUnit": 1.0,
          "rightUnit": 1.0,
          "Forward": {
            "x": 0.0,
            "y": 1.0,
            "z": 0.0
          },
          "Back": {
            "x": 0.0,
            "y": -1.0,
            "z": 0.0
          },
          "Left": {
            "x": -1.0,
            "y": 0.0,
            "z": 0.0
          },
          "Right": {
            "x": 1.0,
            "y": 0.0,
            "z": 0.0
          }
        },
        "Min": {
          "x": 11.0,
          "y": 17.0,
          "z": 1.0
        },
        "Max": {
          "x": 20.0,
          "y": 17.0,
          "z": 1.0
        },
        "DemoList": [
          [
            {
              "x": 12.0,
              "y": 17.0,
              "z": 1.0
            },
            {
              "x": 13.0,
              "y": 17.0,
              "z": 1.0
            },
            {
              "x": 14.0,
              "y": 17.0,
              "z": 1.0
            },
            {
              "x": 15.0,
              "y": 17.0,
              "z": 1.0
            },
            {
              "x": 16.0,
              "y": 17.0,
              "z": 1.0
            }
          ]
        ],
        "Segments": [
          [
            {
              "x": 11.0,
              "y": 17.0,
              "z": 1.0
            },
            {
              "x": 12.0,
              "y": 17.0,
              "z": 1.0
            },
            {
              "x": 13.0,
              "y": 17.0,
              "z": 1.0
            },
            {
              "x": 14.0,
              "y": 17.0,
              "z": 1.0
            },
            {
              "x": 15.0,
              "y": 17.0,
              "z": 1.0
            },
            {
              "x": 16.0,
              "y": 17.0,
              "z": 1.0
            },
            {
              "x": 17.0,
              "y": 17.0,
              "z": 1.0
            },
            {
              "x": 18.0,
              "y": 17.0,
              "z": 1.0
            },
            {
              "x": 19.0,
              "y": 17.0,
              "z": 1.0
            },
            {
              "x": 20.0,
              "y": 17.0,
              "z": 1.0
            }
          ]
        ]
      },
      {
        "Orientation": {
          "Name": "East",
          "foreUnit": 1.0,
          "rightUnit": -1.0,
          "Forward": {
            "x": 1.0,
            "y": 0.0,
            "z": 0.0
          },
          "Back": {
            "x": -1.0,
            "y": 0.0,
            "z": 0.0
          },
          "Left": {
            "x": 0.0,
            "y": 1.0,
            "z": 0.0
          },
          "Right": {
            "x": 0.0,
            "y": -1.0,
            "z": 0.0
          }
        },
        "Min": {
          "x": 20.0,
          "y": 9.0,
          "z": 1.0
        },
        "Max": {
          "x": 20.0,
          "y": 17.0,
          "z": 1.0
        },
        "DemoList": [],
        "Segments": [
          [
            {
              "x": 20.0,
              "y": 9.0,
              "z": 1.0
            },
            {
              "x": 20.0,
              "y": 10.0,
              "z": 1.0
            },
            {
              "x": 20.0,
              "y": 11.0,
              "z": 1.0
            },
            {
              "x": 20.0,
              "y": 12.0,
              "z": 1.0
            },
            {
              "x": 20.0,
              "y": 13.0,
              "z": 1.0
            },
            {
              "x": 20.0,
              "y": 14.0,
              "z": 1.0
            },
            {
              "x": 20.0,
              "y": 15.0,
              "z": 1.0
            },
            {
              "x": 20.0,
              "y": 16.0,
              "z": 1.0
            },
            {
              "x": 20.0,
              "y": 17.0,
              "z": 1.0
            }
          ]
        ]
      },
      {
        "Orientation": {
          "Name": "West",
          "foreUnit": -1.0,
          "rightUnit": 1.0,
          "Forward": {
            "x": -1.0,
            "y": 0.0,
            "z": 0.0
          },
          "Back": {
            "x": 1.0,
            "y": 0.0,
            "z": 0.0
          },
          "Left": {
            "x": 0.0,
            "y": -1.0,
            "z": 0.0
          },
          "Right": {
            "x": 0.0,
            "y": 1.0,
            "z": 0.0
          }
        },
        "Min": {
          "x": 11.0,
          "y": 9.0,
          "z": 1.0
        },
        "Max": {
          "x": 11.0,
          "y": 17.0,
          "z": 1.0
        },
        "DemoList": [
          [
            {
              "x": 11.0,
              "y": 11.0,
              "z": 1.0
            },
            {
              "x": 11.0,
              "y": 12.0,
              "z": 1.0
            }
          ]
        ],
        "Segments": [
          [
            {
              "x": 11.0,
              "y": 9.0,
              "z": 1.0
            },
            {
              "x": 11.0,
              "y": 10.0,
              "z": 1.0
            },
            {
              "x": 11.0,
              "y": 11.0,
              "z": 1.0
            },
            {
              "x": 11.0,
              "y": 12.0,
              "z": 1.0
            },
            {
              "x": 11.0,
              "y": 13.0,
              "z": 1.0
            },
            {
              "x": 11.0,
              "y": 14.0,
              "z": 1.0
            },
            {
              "x": 11.0,
              "y": 15.0,
              "z": 1.0
            },
            {
              "x": 11.0,
              "y": 16.0,
              "z": 1.0
            },
            {
              "x": 11.0,
              "y": 17.0,
              "z": 1.0
            }
          ]
        ]
      }
    ],
    "ConnectedAreas": [
      4,
      6
    ],
    "Orientation": {
      "Name": "South",
      "foreUnit": -1.0,
      "rightUnit": -1.0,
      "Forward": {
        "x": 0.0,
        "y": -1.0,
        "z": 0.0
      },
      "Back": {
        "x": 0.0,
        "y": 1.0,
        "z": 0.0
      },
      "Left": {
        "x": 1.0,
        "y": 0.0,
        "z": 0.0
      },
      "Right": {
        "x": -1.0,
        "y": 0.0,
        "z": 0.0
      }
    },
    "RoomIndex": 5,
    "Floor": {
      "BottomLeft": {
        "x": 19.0,
        "y": 16.0,
        "z": 1.0
      },
      "TopRight": {
        "x": 12.0,
        "y": 10.0,
        "z": 1.0
      },
      "BottomRight": {
        "x": 12.0,
        "y": 16.0,
        "z": 1.0
      },
      "TopLeft": {
        "x": 19.0,
        "y": 10.0,
        "z": 1.0
      },
      "width": 8.0,
      "height": 7.0,
      "Center": {
        "x": 23.0,
        "y": 19.5,
        "z": 1.0
      },
      "TrueSW": {
        "x": 12.0,
        "y": 10.0,
        "z": 1.0
      },
      "TrueNE": {
        "x": 19.0,
        "y": 16.0,
        "z": 1.0
      }
    }
  },
  "6": {
    "creationTime": "2020-01-05T15:47:40.5678869-06:00",
    "Walls": [
      {
        "Orientation": {
          "Name": "South",
          "foreUnit": -1.0,
          "rightUnit": -1.0,
          "Forward": {
            "x": 0.0,
            "y": -1.0,
            "z": 0.0
          },
          "Back": {
            "x": 0.0,
            "y": 1.0,
            "z": 0.0
          },
          "Left": {
            "x": 1.0,
            "y": 0.0,
            "z": 0.0
          },
          "Right": {
            "x": -1.0,
            "y": 0.0,
            "z": 0.0
          }
        },
        "Min": {
          "x": 4.0,
          "y": 5.0,
          "z": 1.0
        },
        "Max": {
          "x": 11.0,
          "y": 5.0,
          "z": 1.0
        },
        "DemoList": [],
        "Segments": [
          [
            {
              "x": 4.0,
              "y": 5.0,
              "z": 1.0
            },
            {
              "x": 5.0,
              "y": 5.0,
              "z": 1.0
            },
            {
              "x": 6.0,
              "y": 5.0,
              "z": 1.0
            },
            {
              "x": 7.0,
              "y": 5.0,
              "z": 1.0
            },
            {
              "x": 8.0,
              "y": 5.0,
              "z": 1.0
            },
            {
              "x": 9.0,
              "y": 5.0,
              "z": 1.0
            },
            {
              "x": 10.0,
              "y": 5.0,
              "z": 1.0
            },
            {
              "x": 11.0,
              "y": 5.0,
              "z": 1.0
            }
          ]
        ]
      },
      {
        "Orientation": {
          "Name": "North",
          "foreUnit": 1.0,
          "rightUnit": 1.0,
          "Forward": {
            "x": 0.0,
            "y": 1.0,
            "z": 0.0
          },
          "Back": {
            "x": 0.0,
            "y": -1.0,
            "z": 0.0
          },
          "Left": {
            "x": -1.0,
            "y": 0.0,
            "z": 0.0
          },
          "Right": {
            "x": 1.0,
            "y": 0.0,
            "z": 0.0
          }
        },
        "Min": {
          "x": 4.0,
          "y": 14.0,
          "z": 1.0
        },
        "Max": {
          "x": 11.0,
          "y": 14.0,
          "z": 1.0
        },
        "DemoList": [],
        "Segments": [
          [
            {
              "x": 4.0,
              "y": 14.0,
              "z": 1.0
            },
            {
              "x": 5.0,
              "y": 14.0,
              "z": 1.0
            },
            {
              "x": 6.0,
              "y": 14.0,
              "z": 1.0
            },
            {
              "x": 7.0,
              "y": 14.0,
              "z": 1.0
            },
            {
              "x": 8.0,
              "y": 14.0,
              "z": 1.0
            },
            {
              "x": 9.0,
              "y": 14.0,
              "z": 1.0
            },
            {
              "x": 10.0,
              "y": 14.0,
              "z": 1.0
            },
            {
              "x": 11.0,
              "y": 14.0,
              "z": 1.0
            }
          ]
        ]
      },
      {
        "Orientation": {
          "Name": "West",
          "foreUnit": -1.0,
          "rightUnit": 1.0,
          "Forward": {
            "x": -1.0,
            "y": 0.0,
            "z": 0.0
          },
          "Back": {
            "x": 1.0,
            "y": 0.0,
            "z": 0.0
          },
          "Left": {
            "x": 0.0,
            "y": -1.0,
            "z": 0.0
          },
          "Right": {
            "x": 0.0,
            "y": 1.0,
            "z": 0.0
          }
        },
        "Min": {
          "x": 4.0,
          "y": 5.0,
          "z": 1.0
        },
        "Max": {
          "x": 4.0,
          "y": 14.0,
          "z": 1.0
        },
        "DemoList": [],
        "Segments": [
          [
            {
              "x": 4.0,
              "y": 5.0,
              "z": 1.0
            },
            {
              "x": 4.0,
              "y": 6.0,
              "z": 1.0
            },
            {
              "x": 4.0,
              "y": 7.0,
              "z": 1.0
            },
            {
              "x": 4.0,
              "y": 8.0,
              "z": 1.0
            },
            {
              "x": 4.0,
              "y": 9.0,
              "z": 1.0
            },
            {
              "x": 4.0,
              "y": 10.0,
              "z": 1.0
            },
            {
              "x": 4.0,
              "y": 11.0,
              "z": 1.0
            },
            {
              "x": 4.0,
              "y": 12.0,
              "z": 1.0
            },
            {
              "x": 4.0,
              "y": 13.0,
              "z": 1.0
            },
            {
              "x": 4.0,
              "y": 14.0,
              "z": 1.0
            }
          ]
        ]
      },
      {
        "Orientation": {
          "Name": "East",
          "foreUnit": 1.0,
          "rightUnit": -1.0,
          "Forward": {
            "x": 1.0,
            "y": 0.0,
            "z": 0.0
          },
          "Back": {
            "x": -1.0,
            "y": 0.0,
            "z": 0.0
          },
          "Left": {
            "x": 0.0,
            "y": 1.0,
            "z": 0.0
          },
          "Right": {
            "x": 0.0,
            "y": -1.0,
            "z": 0.0
          }
        },
        "Min": {
          "x": 11.0,
          "y": 5.0,
          "z": 1.0
        },
        "Max": {
          "x": 11.0,
          "y": 14.0,
          "z": 1.0
        },
        "DemoList": [
          [
            {
              "x": 11.0,
              "y": 13.0,
              "z": 1.0
            },
            {
              "x": 11.0,
              "y": 12.0,
              "z": 1.0
            },
            {
              "x": 11.0,
              "y": 11.0,
              "z": 1.0
            },
            {
              "x": 11.0,
              "y": 10.0,
              "z": 1.0
            }
          ]
        ],
        "Segments": [
          [
            {
              "x": 11.0,
              "y": 5.0,
              "z": 1.0
            },
            {
              "x": 11.0,
              "y": 6.0,
              "z": 1.0
            },
            {
              "x": 11.0,
              "y": 7.0,
              "z": 1.0
            },
            {
              "x": 11.0,
              "y": 8.0,
              "z": 1.0
            },
            {
              "x": 11.0,
              "y": 9.0,
              "z": 1.0
            },
            {
              "x": 11.0,
              "y": 10.0,
              "z": 1.0
            },
            {
              "x": 11.0,
              "y": 11.0,
              "z": 1.0
            },
            {
              "x": 11.0,
              "y": 12.0,
              "z": 1.0
            },
            {
              "x": 11.0,
              "y": 13.0,
              "z": 1.0
            },
            {
              "x": 11.0,
              "y": 14.0,
              "z": 1.0
            }
          ]
        ]
      }
    ],
    "ConnectedAreas": [
      5
    ],
    "Orientation": {
      "Name": "West",
      "foreUnit": -1.0,
      "rightUnit": 1.0,
      "Forward": {
        "x": -1.0,
        "y": 0.0,
        "z": 0.0
      },
      "Back": {
        "x": 1.0,
        "y": 0.0,
        "z": 0.0
      },
      "Left": {
        "x": 0.0,
        "y": -1.0,
        "z": 0.0
      },
      "Right": {
        "x": 0.0,
        "y": 1.0,
        "z": 0.0
      }
    },
    "RoomIndex": 6,
    "Floor": {
      "BottomLeft": {
        "x": 10.0,
        "y": 6.0,
        "z": 1.0
      },
      "TopRight": {
        "x": 5.0,
        "y": 13.0,
        "z": 1.0
      },
      "BottomRight": {
        "x": 10.0,
        "y": 13.0,
        "z": 1.0
      },
      "TopLeft": {
        "x": 5.0,
        "y": 6.0,
        "z": 1.0
      },
      "width": 8.0,
      "height": 6.0,
      "Center": {
        "x": 14.0,
        "y": 16.0,
        "z": 1.0
      },
      "TrueSW": {
        "x": 5.0,
        "y": 6.0,
        "z": 1.0
      },
      "TrueNE": {
        "x": 10.0,
        "y": 13.0,
        "z": 1.0
      }
    }
  },
  "7": {
    "creationTime": "2020-01-05T15:47:40.5688822-06:00",
    "Walls": [
      {
        "Orientation": {
          "Name": "East",
          "foreUnit": 1.0,
          "rightUnit": -1.0,
          "Forward": {
            "x": 1.0,
            "y": 0.0,
            "z": 0.0
          },
          "Back": {
            "x": -1.0,
            "y": 0.0,
            "z": 0.0
          },
          "Left": {
            "x": 0.0,
            "y": 1.0,
            "z": 0.0
          },
          "Right": {
            "x": 0.0,
            "y": -1.0,
            "z": 0.0
          }
        },
        "Min": {
          "x": 30.0,
          "y": 3.0,
          "z": 1.0
        },
        "Max": {
          "x": 30.0,
          "y": 16.0,
          "z": 1.0
        },
        "DemoList": [],
        "Segments": [
          [
            {
              "x": 30.0,
              "y": 3.0,
              "z": 1.0
            },
            {
              "x": 30.0,
              "y": 4.0,
              "z": 1.0
            },
            {
              "x": 30.0,
              "y": 5.0,
              "z": 1.0
            },
            {
              "x": 30.0,
              "y": 6.0,
              "z": 1.0
            },
            {
              "x": 30.0,
              "y": 7.0,
              "z": 1.0
            },
            {
              "x": 30.0,
              "y": 8.0,
              "z": 1.0
            },
            {
              "x": 30.0,
              "y": 9.0,
              "z": 1.0
            },
            {
              "x": 30.0,
              "y": 10.0,
              "z": 1.0
            },
            {
              "x": 30.0,
              "y": 11.0,
              "z": 1.0
            },
            {
              "x": 30.0,
              "y": 12.0,
              "z": 1.0
            },
            {
              "x": 30.0,
              "y": 13.0,
              "z": 1.0
            },
            {
              "x": 30.0,
              "y": 14.0,
              "z": 1.0
            },
            {
              "x": 30.0,
              "y": 15.0,
              "z": 1.0
            },
            {
              "x": 30.0,
              "y": 16.0,
              "z": 1.0
            }
          ]
        ]
      },
      {
        "Orientation": {
          "Name": "West",
          "foreUnit": -1.0,
          "rightUnit": 1.0,
          "Forward": {
            "x": -1.0,
            "y": 0.0,
            "z": 0.0
          },
          "Back": {
            "x": 1.0,
            "y": 0.0,
            "z": 0.0
          },
          "Left": {
            "x": 0.0,
            "y": -1.0,
            "z": 0.0
          },
          "Right": {
            "x": 0.0,
            "y": 1.0,
            "z": 0.0
          }
        },
        "Min": {
          "x": 23.0,
          "y": 3.0,
          "z": 1.0
        },
        "Max": {
          "x": 23.0,
          "y": 16.0,
          "z": 1.0
        },
        "DemoList": [],
        "Segments": [
          [
            {
              "x": 23.0,
              "y": 3.0,
              "z": 1.0
            },
            {
              "x": 23.0,
              "y": 4.0,
              "z": 1.0
            },
            {
              "x": 23.0,
              "y": 5.0,
              "z": 1.0
            },
            {
              "x": 23.0,
              "y": 6.0,
              "z": 1.0
            },
            {
              "x": 23.0,
              "y": 7.0,
              "z": 1.0
            },
            {
              "x": 23.0,
              "y": 8.0,
              "z": 1.0
            },
            {
              "x": 23.0,
              "y": 9.0,
              "z": 1.0
            },
            {
              "x": 23.0,
              "y": 10.0,
              "z": 1.0
            },
            {
              "x": 23.0,
              "y": 11.0,
              "z": 1.0
            },
            {
              "x": 23.0,
              "y": 12.0,
              "z": 1.0
            },
            {
              "x": 23.0,
              "y": 13.0,
              "z": 1.0
            },
            {
              "x": 23.0,
              "y": 14.0,
              "z": 1.0
            },
            {
              "x": 23.0,
              "y": 15.0,
              "z": 1.0
            },
            {
              "x": 23.0,
              "y": 16.0,
              "z": 1.0
            }
          ]
        ]
      },
      {
        "Orientation": {
          "Name": "South",
          "foreUnit": -1.0,
          "rightUnit": -1.0,
          "Forward": {
            "x": 0.0,
            "y": -1.0,
            "z": 0.0
          },
          "Back": {
            "x": 0.0,
            "y": 1.0,
            "z": 0.0
          },
          "Left": {
            "x": 1.0,
            "y": 0.0,
            "z": 0.0
          },
          "Right": {
            "x": -1.0,
            "y": 0.0,
            "z": 0.0
          }
        },
        "Min": {
          "x": 23.0,
          "y": 3.0,
          "z": 1.0
        },
        "Max": {
          "x": 30.0,
          "y": 3.0,
          "z": 1.0
        },
        "DemoList": [],
        "Segments": [
          [
            {
              "x": 23.0,
              "y": 3.0,
              "z": 1.0
            },
            {
              "x": 24.0,
              "y": 3.0,
              "z": 1.0
            },
            {
              "x": 25.0,
              "y": 3.0,
              "z": 1.0
            },
            {
              "x": 26.0,
              "y": 3.0,
              "z": 1.0
            },
            {
              "x": 27.0,
              "y": 3.0,
              "z": 1.0
            },
            {
              "x": 28.0,
              "y": 3.0,
              "z": 1.0
            },
            {
              "x": 29.0,
              "y": 3.0,
              "z": 1.0
            },
            {
              "x": 30.0,
              "y": 3.0,
              "z": 1.0
            }
          ]
        ]
      },
      {
        "Orientation": {
          "Name": "North",
          "foreUnit": 1.0,
          "rightUnit": 1.0,
          "Forward": {
            "x": 0.0,
            "y": 1.0,
            "z": 0.0
          },
          "Back": {
            "x": 0.0,
            "y": -1.0,
            "z": 0.0
          },
          "Left": {
            "x": -1.0,
            "y": 0.0,
            "z": 0.0
          },
          "Right": {
            "x": 1.0,
            "y": 0.0,
            "z": 0.0
          }
        },
        "Min": {
          "x": 23.0,
          "y": 16.0,
          "z": 1.0
        },
        "Max": {
          "x": 30.0,
          "y": 16.0,
          "z": 1.0
        },
        "DemoList": [
          [
            {
              "x": 25.0,
              "y": 16.0,
              "z": 1.0
            },
            {
              "x": 26.0,
              "y": 16.0,
              "z": 1.0
            },
            {
              "x": 27.0,
              "y": 16.0,
              "z": 1.0
            },
            {
              "x": 28.0,
              "y": 16.0,
              "z": 1.0
            },
            {
              "x": 29.0,
              "y": 16.0,
              "z": 1.0
            }
          ]
        ],
        "Segments": [
          [
            {
              "x": 23.0,
              "y": 16.0,
              "z": 1.0
            },
            {
              "x": 24.0,
              "y": 16.0,
              "z": 1.0
            },
            {
              "x": 25.0,
              "y": 16.0,
              "z": 1.0
            },
            {
              "x": 26.0,
              "y": 16.0,
              "z": 1.0
            },
            {
              "x": 27.0,
              "y": 16.0,
              "z": 1.0
            },
            {
              "x": 28.0,
              "y": 16.0,
              "z": 1.0
            },
            {
              "x": 29.0,
              "y": 16.0,
              "z": 1.0
            },
            {
              "x": 30.0,
              "y": 16.0,
              "z": 1.0
            }
          ]
        ]
      }
    ],
    "ConnectedAreas": [
      3
    ],
    "Orientation": {
      "Name": "South",
      "foreUnit": -1.0,
      "rightUnit": -1.0,
      "Forward": {
        "x": 0.0,
        "y": -1.0,
        "z": 0.0
      },
      "Back": {
        "x": 0.0,
        "y": 1.0,
        "z": 0.0
      },
      "Left": {
        "x": 1.0,
        "y": 0.0,
        "z": 0.0
      },
      "Right": {
        "x": -1.0,
        "y": 0.0,
        "z": 0.0
      }
    },
    "RoomIndex": 7,
    "Floor": {
      "BottomLeft": {
        "x": 29.0,
        "y": 15.0,
        "z": 1.0
      },
      "TopRight": {
        "x": 24.0,
        "y": 4.0,
        "z": 1.0
      },
      "BottomRight": {
        "x": 24.0,
        "y": 15.0,
        "z": 1.0
      },
      "TopLeft": {
        "x": 29.0,
        "y": 4.0,
        "z": 1.0
      },
      "width": 6.0,
      "height": 12.0,
      "Center": {
        "x": 32.0,
        "y": 21.0,
        "z": 1.0
      },
      "TrueSW": {
        "x": 24.0,
        "y": 4.0,
        "z": 1.0
      },
      "TrueNE": {
        "x": 29.0,
        "y": 15.0,
        "z": 1.0
      }
    }
  },
  "8": {
    "creationTime": "2020-01-05T15:47:40.5698821-06:00",
    "Walls": [
      {
        "Orientation": {
          "Name": "North",
          "foreUnit": 1.0,
          "rightUnit": 1.0,
          "Forward": {
            "x": 0.0,
            "y": 1.0,
            "z": 0.0
          },
          "Back": {
            "x": 0.0,
            "y": -1.0,
            "z": 0.0
          },
          "Left": {
            "x": -1.0,
            "y": 0.0,
            "z": 0.0
          },
          "Right": {
            "x": 1.0,
            "y": 0.0,
            "z": 0.0
          }
        },
        "Min": {
          "x": 30.0,
          "y": 46.0,
          "z": 1.0
        },
        "Max": {
          "x": 38.0,
          "y": 46.0,
          "z": 1.0
        },
        "DemoList": [],
        "Segments": [
          [
            {
              "x": 30.0,
              "y": 46.0,
              "z": 1.0
            },
            {
              "x": 31.0,
              "y": 46.0,
              "z": 1.0
            },
            {
              "x": 32.0,
              "y": 46.0,
              "z": 1.0
            },
            {
              "x": 33.0,
              "y": 46.0,
              "z": 1.0
            },
            {
              "x": 34.0,
              "y": 46.0,
              "z": 1.0
            },
            {
              "x": 35.0,
              "y": 46.0,
              "z": 1.0
            },
            {
              "x": 36.0,
              "y": 46.0,
              "z": 1.0
            },
            {
              "x": 37.0,
              "y": 46.0,
              "z": 1.0
            },
            {
              "x": 38.0,
              "y": 46.0,
              "z": 1.0
            }
          ]
        ]
      },
      {
        "Orientation": {
          "Name": "South",
          "foreUnit": -1.0,
          "rightUnit": -1.0,
          "Forward": {
            "x": 0.0,
            "y": -1.0,
            "z": 0.0
          },
          "Back": {
            "x": 0.0,
            "y": 1.0,
            "z": 0.0
          },
          "Left": {
            "x": 1.0,
            "y": 0.0,
            "z": 0.0
          },
          "Right": {
            "x": -1.0,
            "y": 0.0,
            "z": 0.0
          }
        },
        "Min": {
          "x": 30.0,
          "y": 35.0,
          "z": 1.0
        },
        "Max": {
          "x": 38.0,
          "y": 35.0,
          "z": 1.0
        },
        "DemoList": [
          [
            {
              "x": 37.0,
              "y": 35.0,
              "z": 1.0
            },
            {
              "x": 36.0,
              "y": 35.0,
              "z": 1.0
            },
            {
              "x": 35.0,
              "y": 35.0,
              "z": 1.0
            },
            {
              "x": 34.0,
              "y": 35.0,
              "z": 1.0
            },
            {
              "x": 33.0,
              "y": 35.0,
              "z": 1.0
            },
            {
              "x": 32.0,
              "y": 35.0,
              "z": 1.0
            },
            {
              "x": 31.0,
              "y": 35.0,
              "z": 1.0
            }
          ]
        ],
        "Segments": [
          [
            {
              "x": 30.0,
              "y": 35.0,
              "z": 1.0
            },
            {
              "x": 31.0,
              "y": 35.0,
              "z": 1.0
            },
            {
              "x": 32.0,
              "y": 35.0,
              "z": 1.0
            },
            {
              "x": 33.0,
              "y": 35.0,
              "z": 1.0
            },
            {
              "x": 34.0,
              "y": 35.0,
              "z": 1.0
            },
            {
              "x": 35.0,
              "y": 35.0,
              "z": 1.0
            },
            {
              "x": 36.0,
              "y": 35.0,
              "z": 1.0
            },
            {
              "x": 37.0,
              "y": 35.0,
              "z": 1.0
            },
            {
              "x": 38.0,
              "y": 35.0,
              "z": 1.0
            }
          ]
        ]
      },
      {
        "Orientation": {
          "Name": "West",
          "foreUnit": -1.0,
          "rightUnit": 1.0,
          "Forward": {
            "x": -1.0,
            "y": 0.0,
            "z": 0.0
          },
          "Back": {
            "x": 1.0,
            "y": 0.0,
            "z": 0.0
          },
          "Left": {
            "x": 0.0,
            "y": -1.0,
            "z": 0.0
          },
          "Right": {
            "x": 0.0,
            "y": 1.0,
            "z": 0.0
          }
        },
        "Min": {
          "x": 30.0,
          "y": 35.0,
          "z": 1.0
        },
        "Max": {
          "x": 30.0,
          "y": 46.0,
          "z": 1.0
        },
        "DemoList": [],
        "Segments": [
          [
            {
              "x": 30.0,
              "y": 35.0,
              "z": 1.0
            },
            {
              "x": 30.0,
              "y": 36.0,
              "z": 1.0
            },
            {
              "x": 30.0,
              "y": 37.0,
              "z": 1.0
            },
            {
              "x": 30.0,
              "y": 38.0,
              "z": 1.0
            },
            {
              "x": 30.0,
              "y": 39.0,
              "z": 1.0
            },
            {
              "x": 30.0,
              "y": 40.0,
              "z": 1.0
            },
            {
              "x": 30.0,
              "y": 41.0,
              "z": 1.0
            },
            {
              "x": 30.0,
              "y": 42.0,
              "z": 1.0
            },
            {
              "x": 30.0,
              "y": 43.0,
              "z": 1.0
            },
            {
              "x": 30.0,
              "y": 44.0,
              "z": 1.0
            },
            {
              "x": 30.0,
              "y": 45.0,
              "z": 1.0
            },
            {
              "x": 30.0,
              "y": 46.0,
              "z": 1.0
            }
          ]
        ]
      },
      {
        "Orientation": {
          "Name": "East",
          "foreUnit": 1.0,
          "rightUnit": -1.0,
          "Forward": {
            "x": 1.0,
            "y": 0.0,
            "z": 0.0
          },
          "Back": {
            "x": -1.0,
            "y": 0.0,
            "z": 0.0
          },
          "Left": {
            "x": 0.0,
            "y": 1.0,
            "z": 0.0
          },
          "Right": {
            "x": 0.0,
            "y": -1.0,
            "z": 0.0
          }
        },
        "Min": {
          "x": 38.0,
          "y": 35.0,
          "z": 1.0
        },
        "Max": {
          "x": 38.0,
          "y": 46.0,
          "z": 1.0
        },
        "DemoList": [
          [
            {
              "x": 38.0,
              "y": 42.0,
              "z": 1.0
            },
            {
              "x": 38.0,
              "y": 43.0,
              "z": 1.0
            },
            {
              "x": 38.0,
              "y": 44.0,
              "z": 1.0
            }
          ]
        ],
        "Segments": [
          [
            {
              "x": 38.0,
              "y": 35.0,
              "z": 1.0
            },
            {
              "x": 38.0,
              "y": 36.0,
              "z": 1.0
            },
            {
              "x": 38.0,
              "y": 37.0,
              "z": 1.0
            },
            {
              "x": 38.0,
              "y": 38.0,
              "z": 1.0
            },
            {
              "x": 38.0,
              "y": 39.0,
              "z": 1.0
            },
            {
              "x": 38.0,
              "y": 40.0,
              "z": 1.0
            },
            {
              "x": 38.0,
              "y": 41.0,
              "z": 1.0
            },
            {
              "x": 38.0,
              "y": 42.0,
              "z": 1.0
            },
            {
              "x": 38.0,
              "y": 43.0,
              "z": 1.0
            },
            {
              "x": 38.0,
              "y": 44.0,
              "z": 1.0
            },
            {
              "x": 38.0,
              "y": 45.0,
              "z": 1.0
            },
            {
              "x": 38.0,
              "y": 46.0,
              "z": 1.0
            }
          ]
        ]
      }
    ],
    "ConnectedAreas": [
      2,
      9
    ],
    "Orientation": {
      "Name": "North",
      "foreUnit": 1.0,
      "rightUnit": 1.0,
      "Forward": {
        "x": 0.0,
        "y": 1.0,
        "z": 0.0
      },
      "Back": {
        "x": 0.0,
        "y": -1.0,
        "z": 0.0
      },
      "Left": {
        "x": -1.0,
        "y": 0.0,
        "z": 0.0
      },
      "Right": {
        "x": 1.0,
        "y": 0.0,
        "z": 0.0
      }
    },
    "RoomIndex": 8,
    "Floor": {
      "BottomLeft": {
        "x": 31.0,
        "y": 36.0,
        "z": 1.0
      },
      "TopRight": {
        "x": 37.0,
        "y": 45.0,
        "z": 1.0
      },
      "BottomRight": {
        "x": 37.0,
        "y": 36.0,
        "z": 1.0
      },
      "TopLeft": {
        "x": 31.0,
        "y": 45.0,
        "z": 1.0
      },
      "width": 7.0,
      "height": 10.0,
      "Center": {
        "x": 34.5,
        "y": 41.0,
        "z": 1.0
      },
      "TrueSW": {
        "x": 31.0,
        "y": 36.0,
        "z": 1.0
      },
      "TrueNE": {
        "x": 37.0,
        "y": 45.0,
        "z": 1.0
      }
    }
  },
  "9": {
    "creationTime": "2020-01-05T15:47:40.5708769-06:00",
    "Walls": [
      {
        "Orientation": {
          "Name": "East",
          "foreUnit": 1.0,
          "rightUnit": -1.0,
          "Forward": {
            "x": 1.0,
            "y": 0.0,
            "z": 0.0
          },
          "Back": {
            "x": -1.0,
            "y": 0.0,
            "z": 0.0
          },
          "Left": {
            "x": 0.0,
            "y": 1.0,
            "z": 0.0
          },
          "Right": {
            "x": 0.0,
            "y": -1.0,
            "z": 0.0
          }
        },
        "Min": {
          "x": 48.0,
          "y": 37.0,
          "z": 1.0
        },
        "Max": {
          "x": 48.0,
          "y": 44.0,
          "z": 1.0
        },
        "DemoList": [],
        "Segments": [
          [
            {
              "x": 48.0,
              "y": 37.0,
              "z": 1.0
            },
            {
              "x": 48.0,
              "y": 38.0,
              "z": 1.0
            },
            {
              "x": 48.0,
              "y": 39.0,
              "z": 1.0
            },
            {
              "x": 48.0,
              "y": 40.0,
              "z": 1.0
            },
            {
              "x": 48.0,
              "y": 41.0,
              "z": 1.0
            },
            {
              "x": 48.0,
              "y": 42.0,
              "z": 1.0
            },
            {
              "x": 48.0,
              "y": 43.0,
              "z": 1.0
            },
            {
              "x": 48.0,
              "y": 44.0,
              "z": 1.0
            }
          ]
        ]
      },
      {
        "Orientation": {
          "Name": "North",
          "foreUnit": 1.0,
          "rightUnit": 1.0,
          "Forward": {
            "x": 0.0,
            "y": 1.0,
            "z": 0.0
          },
          "Back": {
            "x": 0.0,
            "y": -1.0,
            "z": 0.0
          },
          "Left": {
            "x": -1.0,
            "y": 0.0,
            "z": 0.0
          },
          "Right": {
            "x": 1.0,
            "y": 0.0,
            "z": 0.0
          }
        },
        "Min": {
          "x": 38.0,
          "y": 44.0,
          "z": 1.0
        },
        "Max": {
          "x": 48.0,
          "y": 44.0,
          "z": 1.0
        },
        "DemoList": [],
        "Segments": [
          [
            {
              "x": 38.0,
              "y": 44.0,
              "z": 1.0
            },
            {
              "x": 39.0,
              "y": 44.0,
              "z": 1.0
            },
            {
              "x": 40.0,
              "y": 44.0,
              "z": 1.0
            },
            {
              "x": 41.0,
              "y": 44.0,
              "z": 1.0
            },
            {
              "x": 42.0,
              "y": 44.0,
              "z": 1.0
            },
            {
              "x": 43.0,
              "y": 44.0,
              "z": 1.0
            },
            {
              "x": 44.0,
              "y": 44.0,
              "z": 1.0
            },
            {
              "x": 45.0,
              "y": 44.0,
              "z": 1.0
            },
            {
              "x": 46.0,
              "y": 44.0,
              "z": 1.0
            },
            {
              "x": 47.0,
              "y": 44.0,
              "z": 1.0
            },
            {
              "x": 48.0,
              "y": 44.0,
              "z": 1.0
            }
          ]
        ]
      },
      {
        "Orientation": {
          "Name": "West",
          "foreUnit": -1.0,
          "rightUnit": 1.0,
          "Forward": {
            "x": -1.0,
            "y": 0.0,
            "z": 0.0
          },
          "Back": {
            "x": 1.0,
            "y": 0.0,
            "z": 0.0
          },
          "Left": {
            "x": 0.0,
            "y": -1.0,
            "z": 0.0
          },
          "Right": {
            "x": 0.0,
            "y": 1.0,
            "z": 0.0
          }
        },
        "Min": {
          "x": 38.0,
          "y": 37.0,
          "z": 1.0
        },
        "Max": {
          "x": 38.0,
          "y": 44.0,
          "z": 1.0
        },
        "DemoList": [
          [
            {
              "x": 38.0,
              "y": 38.0,
              "z": 1.0
            },
            {
              "x": 38.0,
              "y": 39.0,
              "z": 1.0
            },
            {
              "x": 38.0,
              "y": 40.0,
              "z": 1.0
            },
            {
              "x": 38.0,
              "y": 41.0,
              "z": 1.0
            },
            {
              "x": 38.0,
              "y": 42.0,
              "z": 1.0
            },
            {
              "x": 38.0,
              "y": 43.0,
              "z": 1.0
            }
          ]
        ],
        "Segments": [
          [
            {
              "x": 38.0,
              "y": 37.0,
              "z": 1.0
            },
            {
              "x": 38.0,
              "y": 38.0,
              "z": 1.0
            },
            {
              "x": 38.0,
              "y": 39.0,
              "z": 1.0
            },
            {
              "x": 38.0,
              "y": 40.0,
              "z": 1.0
            },
            {
              "x": 38.0,
              "y": 41.0,
              "z": 1.0
            },
            {
              "x": 38.0,
              "y": 42.0,
              "z": 1.0
            },
            {
              "x": 38.0,
              "y": 43.0,
              "z": 1.0
            },
            {
              "x": 38.0,
              "y": 44.0,
              "z": 1.0
            }
          ]
        ]
      },
      {
        "Orientation": {
          "Name": "South",
          "foreUnit": -1.0,
          "rightUnit": -1.0,
          "Forward": {
            "x": 0.0,
            "y": -1.0,
            "z": 0.0
          },
          "Back": {
            "x": 0.0,
            "y": 1.0,
            "z": 0.0
          },
          "Left": {
            "x": 1.0,
            "y": 0.0,
            "z": 0.0
          },
          "Right": {
            "x": -1.0,
            "y": 0.0,
            "z": 0.0
          }
        },
        "Min": {
          "x": 38.0,
          "y": 37.0,
          "z": 1.0
        },
        "Max": {
          "x": 48.0,
          "y": 37.0,
          "z": 1.0
        },
        "DemoList": [],
        "Segments": [
          [
            {
              "x": 38.0,
              "y": 37.0,
              "z": 1.0
            },
            {
              "x": 39.0,
              "y": 37.0,
              "z": 1.0
            },
            {
              "x": 40.0,
              "y": 37.0,
              "z": 1.0
            },
            {
              "x": 41.0,
              "y": 37.0,
              "z": 1.0
            },
            {
              "x": 42.0,
              "y": 37.0,
              "z": 1.0
            },
            {
              "x": 43.0,
              "y": 37.0,
              "z": 1.0
            },
            {
              "x": 44.0,
              "y": 37.0,
              "z": 1.0
            },
            {
              "x": 45.0,
              "y": 37.0,
              "z": 1.0
            },
            {
              "x": 46.0,
              "y": 37.0,
              "z": 1.0
            },
            {
              "x": 47.0,
              "y": 37.0,
              "z": 1.0
            },
            {
              "x": 48.0,
              "y": 37.0,
              "z": 1.0
            }
          ]
        ]
      }
    ],
    "ConnectedAreas": [
      8
    ],
    "Orientation": {
      "Name": "East",
      "foreUnit": 1.0,
      "rightUnit": -1.0,
      "Forward": {
        "x": 1.0,
        "y": 0.0,
        "z": 0.0
      },
      "Back": {
        "x": -1.0,
        "y": 0.0,
        "z": 0.0
      },
      "Left": {
        "x": 0.0,
        "y": 1.0,
        "z": 0.0
      },
      "Right": {
        "x": 0.0,
        "y": -1.0,
        "z": 0.0
      }
    },
    "RoomIndex": 9,
    "Floor": {
      "BottomLeft": {
        "x": 39.0,
        "y": 43.0,
        "z": 1.0
      },
      "TopRight": {
        "x": 47.0,
        "y": 38.0,
        "z": 1.0
      },
      "BottomRight": {
        "x": 39.0,
        "y": 38.0,
        "z": 1.0
      },
      "TopLeft": {
        "x": 47.0,
        "y": 43.0,
        "z": 1.0
      },
      "width": 6.0,
      "height": 9.0,
      "Center": {
        "x": 42.0,
        "y": 42.5,
        "z": 1.0
      },
      "TrueSW": {
        "x": 39.0,
        "y": 38.0,
        "z": 1.0
      },
      "TrueNE": {
        "x": 47.0,
        "y": 43.0,
        "z": 1.0
      }
    }
  }
}